gym_pandas/__init__.py
gym_pandas/envs/__init__.py
gym_pandas/envs/pandas_env.py
gym_pandas-0.0.1.dist-info/METADATA
gym_pandas-0.0.1.dist-info/WHEEL
gym_pandas-0.0.1.dist-info/top_level.txt
gym_pandas-0.0.1.dist-info/RECORD
