Metadata-Version: 2.1
Name: gym-pandas
Version: 0.0.1
Summary: An OpenAI Gym Env for Pandas
Home-page: UNKNOWN
License: UNKNOWN
Platform: UNKNOWN
Requires-Dist: gym
